smartyaml/__init__.py
smartyaml/smartyaml.py
smartyaml-0.1.4.dist-info/LICENSE
smartyaml-0.1.4.dist-info/METADATA
smartyaml-0.1.4.dist-info/WHEEL
smartyaml-0.1.4.dist-info/top_level.txt
smartyaml-0.1.4.dist-info/RECORD
