Metadata-Version: 2.1
Name: smartyaml
Version: 0.1.4
Summary: SMART Yaml library
Home-page: UNKNOWN
Author: Foo, Ji-Haw
Author-email: foojihaw@hotmail.com
License: BSD 2-Clause
Platform: UNKNOWN
